shear_psf_leakage/__init__.py
shear_psf_leakage/correlation.py
shear_psf_leakage/leakage.py
shear_psf_leakage/leakage_object.py
shear_psf_leakage/leakage_scale.py
shear_psf_leakage/plot_style.py
shear_psf_leakage/plots.py
shear_psf_leakage/rho_tau_cov.py
shear_psf_leakage/rho_tau_stat.py
shear_psf_leakage/run_object.py
shear_psf_leakage/run_scale.py
shear_psf_leakage/transform_to_notebooks.py
shear_psf_leakage-0.2.1.dist-info/LICENSE
shear_psf_leakage-0.2.1.dist-info/METADATA
shear_psf_leakage-0.2.1.dist-info/WHEEL
shear_psf_leakage-0.2.1.dist-info/entry_points.txt
shear_psf_leakage-0.2.1.dist-info/RECORD
